{
    "ChampionName": {
        "lower": "malphite", 
        "pretty": "Malphite"
    }, 
    "WeakAgainst": [
        {
            "champName": "Rumble", 
            "downvotes": "938", 
            "upvotes": "2811"
        }, 
        {
            "champName": "Yorick", 
            "downvotes": "532", 
            "upvotes": "1279"
        }, 
        {
            "champName": "Cho'Gath", 
            "downvotes": "790", 
            "upvotes": "1694"
        }, 
        {
            "champName": "Darius", 
            "downvotes": "109", 
            "upvotes": "232"
        }, 
        {
            "champName": "Vladimir", 
            "downvotes": "1312", 
            "upvotes": "2067"
        }, 
        {
            "champName": "Garen", 
            "downvotes": "176", 
            "upvotes": "324"
        }, 
        {
            "champName": "Zac", 
            "downvotes": "210", 
            "upvotes": "372"
        }, 
        {
            "champName": "Riven", 
            "downvotes": "373", 
            "upvotes": "611"
        }, 
        {
            "champName": "Aatrox", 
            "downvotes": "49", 
            "upvotes": "130"
        }, 
        {
            "champName": "Nasus", 
            "downvotes": "339", 
            "upvotes": "539"
        }
    ], 
    "StrongAgainst": [
        {
            "champName": "Jax", 
            "downvotes": "2881", 
            "upvotes": "10265"
        }, 
        {
            "champName": "Fiora", 
            "downvotes": "721", 
            "upvotes": "1934"
        }, 
        {
            "champName": "Xin Zhao", 
            "downvotes": "539", 
            "upvotes": "1430"
        }, 
        {
            "champName": "Tryndamere", 
            "downvotes": "1146", 
            "upvotes": "2114"
        }, 
        {
            "champName": "Yasuo", 
            "downvotes": "61", 
            "upvotes": "163"
        }, 
        {
            "champName": "Xin Zhao", 
            "downvotes": "495", 
            "upvotes": "810"
        }, 
        {
            "champName": "Riven", 
            "downvotes": "320", 
            "upvotes": "531"
        }, 
        {
            "champName": "Aatrox", 
            "downvotes": "225", 
            "upvotes": "389"
        }, 
        {
            "champName": "Jax", 
            "downvotes": "25", 
            "upvotes": "94"
        }, 
        {
            "champName": "Teemo", 
            "downvotes": "254", 
            "upvotes": "425"
        }
    ], 
    "ChampionImageLocation": "http://www.solomid.net/guide/champ/malphite.png", 
    "GoodWith": [
        {
            "champName": "Yasuo", 
            "downvotes": "153", 
            "upvotes": "843"
        }, 
        {
            "champName": "Orianna", 
            "downvotes": "525", 
            "upvotes": "1875"
        }, 
        {
            "champName": "Lulu", 
            "downvotes": "57", 
            "upvotes": "156"
        }, 
        {
            "champName": "Amumu", 
            "downvotes": "179", 
            "upvotes": "376"
        }, 
        {
            "champName": "Katarina", 
            "downvotes": "383", 
            "upvotes": "739"
        }, 
        {
            "champName": "Kennen", 
            "downvotes": "58", 
            "upvotes": "140"
        }, 
        {
            "champName": "Jarvan IV", 
            "downvotes": "24", 
            "upvotes": "78"
        }, 
        {
            "champName": "Aatrox", 
            "downvotes": "25", 
            "upvotes": "72"
        }, 
        {
            "champName": "Ashe", 
            "downvotes": "19", 
            "upvotes": "60"
        }, 
        {
            "champName": "Wukong", 
            "downvotes": "67", 
            "upvotes": "132"
        }
    ]
}