{
    "ChampionName": {
        "lower": "riven", 
        "pretty": "Riven"
    }, 
    "WeakAgainst": [
        {
            "champName": "Garen", 
            "downvotes": "4183", 
            "upvotes": "12238"
        }, 
        {
            "champName": "Olaf", 
            "downvotes": "3108", 
            "upvotes": "7083"
        }, 
        {
            "champName": "Kennen", 
            "downvotes": "1349", 
            "upvotes": "3060"
        }, 
        {
            "champName": "Renekton", 
            "downvotes": "2630", 
            "upvotes": "5218"
        }, 
        {
            "champName": "Shyvana", 
            "downvotes": "578", 
            "upvotes": "1158"
        }, 
        {
            "champName": "Jax", 
            "downvotes": "2798", 
            "upvotes": "5309"
        }, 
        {
            "champName": "Pantheon", 
            "downvotes": "943", 
            "upvotes": "1826"
        }, 
        {
            "champName": "LeBlanc", 
            "downvotes": "71", 
            "upvotes": "202"
        }, 
        {
            "champName": "Aatrox", 
            "downvotes": "172", 
            "upvotes": "377"
        }, 
        {
            "champName": "Fiora", 
            "downvotes": "754", 
            "upvotes": "1408"
        }
    ], 
    "StrongAgainst": [
        {
            "champName": "Yasuo", 
            "downvotes": "1484", 
            "upvotes": "3669"
        }, 
        {
            "champName": "Katarina", 
            "downvotes": "153", 
            "upvotes": "434"
        }, 
        {
            "champName": "Aatrox", 
            "downvotes": "1283", 
            "upvotes": "2726"
        }, 
        {
            "champName": "Katarina", 
            "downvotes": "36", 
            "upvotes": "148"
        }, 
        {
            "champName": "Dr. Mundo", 
            "downvotes": "539", 
            "upvotes": "1080"
        }, 
        {
            "champName": "Diana", 
            "downvotes": "1139", 
            "upvotes": "2161"
        }, 
        {
            "champName": "Vladimir", 
            "downvotes": "1613", 
            "upvotes": "2999"
        }, 
        {
            "champName": "Aatrox", 
            "downvotes": "56", 
            "upvotes": "173"
        }, 
        {
            "champName": "Fizz", 
            "downvotes": "136", 
            "upvotes": "317"
        }, 
        {
            "champName": "Vel'Koz", 
            "downvotes": "129", 
            "upvotes": "303"
        }
    ], 
    "ChampionImageLocation": "http://www.solomid.net/guide/champ/riven.png", 
    "GoodWith": [
        {
            "champName": "Yasuo", 
            "downvotes": "13", 
            "upvotes": "80"
        }, 
        {
            "champName": "Vi", 
            "downvotes": "12", 
            "upvotes": "57"
        }, 
        {
            "champName": "Aatrox", 
            "downvotes": "64", 
            "upvotes": "141"
        }, 
        {
            "champName": "Orianna", 
            "downvotes": "298", 
            "upvotes": "451"
        }, 
        {
            "champName": "Ahri", 
            "downvotes": "251", 
            "upvotes": "382"
        }, 
        {
            "champName": "Amumu", 
            "downvotes": "324", 
            "upvotes": "480"
        }, 
        {
            "champName": "Irelia", 
            "downvotes": "929", 
            "upvotes": "1296"
        }, 
        {
            "champName": "Jarvan IV", 
            "downvotes": "22", 
            "upvotes": "56"
        }, 
        {
            "champName": "Jax", 
            "downvotes": "12", 
            "upvotes": "42"
        }, 
        {
            "champName": "Shyvana", 
            "downvotes": "76", 
            "upvotes": "116"
        }
    ]
}